{
  "name": "FlagResultNode",
  "kind": "OBJECT",
  "fields": [
    {
      "name": "created",
      "description": "",
      "type": {
        "kind": "NON_NULL",
        "ofType": {
          "name": "DateTime",
          "kind": "SCALAR"
        }
      }
    },
    {
      "name": "modified",
      "description": "",
      "type": {
        "kind": "NON_NULL",
        "ofType": {
          "name": "DateTime",
          "kind": "SCALAR"
        }
      }
    },
    {
      "name": "reviewer",
      "description": "",
      "type": {
        "name": "PrivateContestUserNode",
        "kind": "OBJECT"
      }
    },
    {
      "name": "status",
      "description": "",
      "type": {
        "kind": "NON_NULL",
        "ofType": {
          "name": "FlagResultStatus",
          "kind": "ENUM"
        }
      }
    }
  ]
}
