{
  "name": "QuestionActivityNode",
  "kind": "OBJECT",
  "fields": [
    {
      "name": "activityType",
      "isDeprecated": false,
      "type": {
        "kind": "NON_NULL",
        "ofType": {
          "name": "LibraryActivityType",
          "kind": "OBJECT"
        }
      }
    },
    {
      "name": "dateCreated",
      "description": "",
      "isDeprecated": false,
      "type": {
        "kind": "NON_NULL",
        "ofType": {
          "name": "DateTime",
          "kind": "SCALAR"
        }
      }
    },
    {
      "name": "id",
      "description": "The ID of the object.",
      "isDeprecated": false,
      "type": {
        "kind": "NON_NULL",
        "ofType": {
          "name": "ID",
          "kind": "SCALAR"
        }
      }
    },
    {
      "name": "isBaseline",
      "description": "",
      "isDeprecated": false,
      "type": {
        "kind": "NON_NULL",
        "ofType": {
          "name": "Boolean",
          "kind": "SCALAR"
        }
      }
    },
    {
      "name": "payload",
      "isDeprecated": false,
      "type": {
        "name": "String",
        "kind": "SCALAR"
      }
    },
    {
      "name": "question",
      "description": "",
      "isDeprecated": false,
      "type": {
        "kind": "NON_NULL",
        "ofType": {
          "name": "LibraryQuestionNode",
          "kind": "OBJECT"
        }
      }
    },
    {
      "name": "user",
      "description": "",
      "isDeprecated": false,
      "type": {
        "name": "PrivateContestUserNode",
        "kind": "OBJECT"
      }
    }
  ]
}
